[
    {
        "query_name": "2007_004143",
        "support_name": "2011_000482"
    },
    {
        "query_name": "2008_001260",
        "support_name": "2008_001040"
    },
    {
        "query_name": "2008_002429",
        "support_name": "2009_001314"
    },
    {
        "query_name": "2009_000440",
        "support_name": "2009_000387"
    },
    {
        "query_name": "2009_003640",
        "support_name": "2011_000482"
    },
    {
        "query_name": "2010_000572",
        "support_name": "2008_003876"
    },
    {
        "query_name": "2010_000961",
        "support_name": "2009_005262"
    },
    {
        "query_name": "2010_001069",
        "support_name": "2009_001160"
    },
    {
        "query_name": "2010_003716",
        "support_name": "2007_005600"
    },
    {
        "query_name": "2011_000874",
        "support_name": "2010_003127"
    },
    {
        "query_name": "2011_001114",
        "support_name": "2011_000874"
    },
    {
        "query_name": "2011_001407",
        "support_name": "2008_003369"
    },
    {
        "query_name": "2007_002400",
        "support_name": "2010_004994"
    },
    {
        "query_name": "2007_008051",
        "support_name": "2011_000669"
    },
    {
        "query_name": "2008_002358",
        "support_name": "2010_005718"
    },
    {
        "query_name": "2008_003369",
        "support_name": "2010_000238"
    },
    {
        "query_name": "2009_000446",
        "support_name": "2009_003504"
    },
    {
        "query_name": "2009_003640",
        "support_name": "2010_005428"
    },
    {
        "query_name": "2010_000241",
        "support_name": "2009_001565"
    },
    {
        "query_name": "2010_000572",
        "support_name": "2007_005600"
    },
    {
        "query_name": "2010_000622",
        "support_name": "2009_001851"
    },
    {
        "query_name": "2007_001568",
        "support_name": "2010_005888"
    },
    {
        "query_name": "2007_004143",
        "support_name": "2009_001565"
    },
    {
        "query_name": "2008_003976",
        "support_name": "2010_000238"
    },
    {
        "query_name": "2008_007120",
        "support_name": "2011_000669"
    },
    {
        "query_name": "2009_000446",
        "support_name": "2010_000084"
    },
    {
        "query_name": "2009_000828",
        "support_name": "2009_003707"
    },
    {
        "query_name": "2009_001683",
        "support_name": "2009_003450"
    },
    {
        "query_name": "2009_003696",
        "support_name": "2007_001884"
    },
    {
        "query_name": "2009_003806",
        "support_name": "2007_006946"
    },
    {
        "query_name": "2010_000272",
        "support_name": "2007_003571"
    },
    {
        "query_name": "2010_000961",
        "support_name": "2011_003145"
    },
    {
        "query_name": "2010_003495",
        "support_name": "2011_002929"
    },
    {
        "query_name": "2011_001114",
        "support_name": "2009_001851"
    },
    {
        "query_name": "2011_001287",
        "support_name": "2009_003498"
    },
    {
        "query_name": "2007_001761",
        "support_name": "2008_003876"
    },
    {
        "query_name": "2008_003976",
        "support_name": "2008_003369"
    },
    {
        "query_name": "2008_007120",
        "support_name": "2009_003498"
    },
    {
        "query_name": "2009_000440",
        "support_name": "2010_005888"
    },
    {
        "query_name": "2009_003696",
        "support_name": "2010_003127"
    },
    {
        "query_name": "2009_003806",
        "support_name": "2008_003926"
    },
    {
        "query_name": "2010_000272",
        "support_name": "2011_000238"
    },
    {
        "query_name": "2010_000572",
        "support_name": "2010_005718"
    },
    {
        "query_name": "2010_003418",
        "support_name": "2010_004994"
    },
    {
        "query_name": "2010_003716",
        "support_name": "2010_003495"
    },
    {
        "query_name": "2010_004419",
        "support_name": "2010_003495"
    },
    {
        "query_name": "2011_001407",
        "support_name": "2007_006946"
    },
    {
        "query_name": "2008_001546",
        "support_name": "2010_005718"
    },
    {
        "query_name": "2008_002429",
        "support_name": "2009_004084"
    },
    {
        "query_name": "2008_003110",
        "support_name": "2009_000991"
    },
    {
        "query_name": "2009_000446",
        "support_name": "2008_003886"
    },
    {
        "query_name": "2009_001683",
        "support_name": "2011_003145"
    },
    {
        "query_name": "2010_000241",
        "support_name": "2009_003450"
    },
    {
        "query_name": "2010_000622",
        "support_name": "2007_006946"
    },
    {
        "query_name": "2010_001069",
        "support_name": "2009_001314"
    },
    {
        "query_name": "2010_004419",
        "support_name": "2011_001434"
    },
    {
        "query_name": "2010_004520",
        "support_name": "2007_009687"
    },
    {
        "query_name": "2010_005534",
        "support_name": "2010_005888"
    },
    {
        "query_name": "2007_003349",
        "support_name": "2009_005262"
    },
    {
        "query_name": "2007_007084",
        "support_name": "2009_001565"
    },
    {
        "query_name": "2008_001260",
        "support_name": "2011_001161"
    },
    {
        "query_name": "2008_002429",
        "support_name": "2010_001995"
    },
    {
        "query_name": "2008_003369",
        "support_name": "2010_001448"
    },
    {
        "query_name": "2009_000387",
        "support_name": "2007_006946"
    },
    {
        "query_name": "2009_000446",
        "support_name": "2008_001135"
    },
    {
        "query_name": "2009_001565",
        "support_name": "2009_004084"
    },
    {
        "query_name": "2009_001683",
        "support_name": "2008_007498"
    },
    {
        "query_name": "2009_003450",
        "support_name": "2008_007498"
    },
    {
        "query_name": "2009_003696",
        "support_name": "2010_003716"
    },
    {
        "query_name": "2009_003806",
        "support_name": "2008_006703"
    },
    {
        "query_name": "2010_002147",
        "support_name": "2008_006703"
    },
    {
        "query_name": "2010_003716",
        "support_name": "2008_003876"
    },
    {
        "query_name": "2010_004419",
        "support_name": "2011_002929"
    },
    {
        "query_name": "2010_004529",
        "support_name": "2010_005496"
    },
    {
        "query_name": "2011_000874",
        "support_name": "2008_003926"
    },
    {
        "query_name": "2011_001407",
        "support_name": "2011_002929"
    },
    {
        "query_name": "2008_001546",
        "support_name": "2010_003365"
    },
    {
        "query_name": "2008_003369",
        "support_name": "2010_003716"
    },
    {
        "query_name": "2009_000440",
        "support_name": "2011_001434"
    },
    {
        "query_name": "2009_000446",
        "support_name": "2011_001161"
    },
    {
        "query_name": "2009_003640",
        "support_name": "2009_000991"
    },
    {
        "query_name": "2009_003696",
        "support_name": "2008_003876"
    },
    {
        "query_name": "2010_000272",
        "support_name": "2007_004241"
    },
    {
        "query_name": "2010_003495",
        "support_name": "2010_001448"
    },
    {
        "query_name": "2010_004419",
        "support_name": "2010_000238"
    },
    {
        "query_name": "2007_001761",
        "support_name": "2008_003926"
    },
    {
        "query_name": "2007_004241",
        "support_name": "2011_000238"
    },
    {
        "query_name": "2007_008051",
        "support_name": "2010_001995"
    },
    {
        "query_name": "2008_001546",
        "support_name": "2010_003127"
    },
    {
        "query_name": "2008_002429",
        "support_name": "2009_001314"
    },
    {
        "query_name": "2008_007120",
        "support_name": "2010_004994"
    },
    {
        "query_name": "2009_000387",
        "support_name": "2008_006703"
    },
    {
        "query_name": "2009_000446",
        "support_name": "2010_004041"
    },
    {
        "query_name": "2009_001332",
        "support_name": "2010_003127"
    },
    {
        "query_name": "2009_003640",
        "support_name": "2011_000482"
    },
    {
        "query_name": "2009_003806",
        "support_name": "2010_005718"
    },
    {
        "query_name": "2010_000241",
        "support_name": "2008_007498"
    },
    {
        "query_name": "2010_000572",
        "support_name": "2007_006946"
    },
    {
        "query_name": "2010_001069",
        "support_name": "2009_003498"
    },
    {
        "query_name": "2010_003495",
        "support_name": "2010_005888"
    },
    {
        "query_name": "2010_005534",
        "support_name": "2007_001884"
    },
    {
        "query_name": "2011_001114",
        "support_name": "2008_003876"
    },
    {
        "query_name": "2011_001287",
        "support_name": "2007_008051"
    },
    {
        "query_name": "2007_004241",
        "support_name": "2008_001135"
    },
    {
        "query_name": "2007_008051",
        "support_name": "2011_002295"
    },
    {
        "query_name": "2007_009911",
        "support_name": "2008_003369"
    },
    {
        "query_name": "2008_002358",
        "support_name": "2011_001434"
    },
    {
        "query_name": "2008_002429",
        "support_name": "2009_001160"
    },
    {
        "query_name": "2008_003369",
        "support_name": "2009_000387"
    },
    {
        "query_name": "2008_003976",
        "support_name": "2010_003716"
    },
    {
        "query_name": "2008_007120",
        "support_name": "2007_008051"
    },
    {
        "query_name": "2009_000440",
        "support_name": "2010_000238"
    },
    {
        "query_name": "2009_000446",
        "support_name": "2010_004662"
    },
    {
        "query_name": "2009_003696",
        "support_name": "2010_003127"
    },
    {
        "query_name": "2009_003806",
        "support_name": "2007_001884"
    },
    {
        "query_name": "2010_000622",
        "support_name": "2010_003716"
    },
    {
        "query_name": "2010_001069",
        "support_name": "2010_005428"
    },
    {
        "query_name": "2010_003716",
        "support_name": "2008_003369"
    },
    {
        "query_name": "2011_001407",
        "support_name": "2008_006703"
    },
    {
        "query_name": "2008_002358",
        "support_name": "2008_005338"
    },
    {
        "query_name": "2008_002429",
        "support_name": "2009_001314"
    },
    {
        "query_name": "2008_003110",
        "support_name": "2008_002043"
    },
    {
        "query_name": "2008_003369",
        "support_name": "2010_003716"
    },
    {
        "query_name": "2009_000446",
        "support_name": "2008_001040"
    },
    {
        "query_name": "2009_001565",
        "support_name": "2009_003450"
    },
    {
        "query_name": "2009_002649",
        "support_name": "2010_005496"
    },
    {
        "query_name": "2010_000622",
        "support_name": "2010_000238"
    },
    {
        "query_name": "2011_001114",
        "support_name": "2008_005338"
    },
    {
        "query_name": "2007_004143",
        "support_name": "2010_005428"
    },
    {
        "query_name": "2009_000440",
        "support_name": "2007_006946"
    },
    {
        "query_name": "2009_000828",
        "support_name": "2010_000084"
    },
    {
        "query_name": "2009_001332",
        "support_name": "2011_002929"
    },
    {
        "query_name": "2010_000241",
        "support_name": "2009_003498"
    },
    {
        "query_name": "2010_000272",
        "support_name": "2009_003080"
    },
    {
        "query_name": "2010_001069",
        "support_name": "2008_007498"
    },
    {
        "query_name": "2010_003418",
        "support_name": "2008_007498"
    },
    {
        "query_name": "2010_004419",
        "support_name": "2008_006703"
    },
    {
        "query_name": "2011_001114",
        "support_name": "2010_003495"
    },
    {
        "query_name": "2011_001287",
        "support_name": "2011_000669"
    },
    {
        "query_name": "2008_001546",
        "support_name": "2009_000387"
    },
    {
        "query_name": "2008_003369",
        "support_name": "2007_001884"
    },
    {
        "query_name": "2008_003976",
        "support_name": "2009_001851"
    },
    {
        "query_name": "2009_000828",
        "support_name": "2009_003707"
    },
    {
        "query_name": "2009_001332",
        "support_name": "2008_003369"
    },
    {
        "query_name": "2009_003640",
        "support_name": "2009_000991"
    },
    {
        "query_name": "2010_000961",
        "support_name": "2011_002295"
    },
    {
        "query_name": "2010_001069",
        "support_name": "2011_000482"
    },
    {
        "query_name": "2010_005534",
        "support_name": "2008_006703"
    },
    {
        "query_name": "2011_000874",
        "support_name": "2010_001448"
    },
    {
        "query_name": "2011_001407",
        "support_name": "2010_003716"
    },
    {
        "query_name": "2007_001761",
        "support_name": "2009_001851"
    },
    {
        "query_name": "2007_002400",
        "support_name": "2009_004886"
    },
    {
        "query_name": "2008_001260",
        "support_name": "2009_003707"
    },
    {
        "query_name": "2008_002429",
        "support_name": "2011_003145"
    },
    {
        "query_name": "2009_000387",
        "support_name": "2008_005338"
    },
    {
        "query_name": "2009_000828",
        "support_name": "2010_000084"
    },
    {
        "query_name": "2009_001565",
        "support_name": "2010_004994"
    },
    {
        "query_name": "2009_001683",
        "support_name": "2008_002043"
    },
    {
        "query_name": "2009_003806",
        "support_name": "2009_000387"
    },
    {
        "query_name": "2010_000272",
        "support_name": "2008_001135"
    },
    {
        "query_name": "2010_000961",
        "support_name": "2008_002043"
    },
    {
        "query_name": "2010_001069",
        "support_name": "2011_000669"
    },
    {
        "query_name": "2011_001407",
        "support_name": "2007_001884"
    },
    {
        "query_name": "2007_007084",
        "support_name": "2007_008051"
    },
    {
        "query_name": "2007_008051",
        "support_name": "2009_004084"
    },
    {
        "query_name": "2008_003369",
        "support_name": "2010_005718"
    },
    {
        "query_name": "2008_003858",
        "support_name": "2008_001580"
    },
    {
        "query_name": "2009_000440",
        "support_name": "2008_006703"
    },
    {
        "query_name": "2009_000828",
        "support_name": "2007_004241"
    },
    {
        "query_name": "2010_000272",
        "support_name": "2007_003571"
    },
    {
        "query_name": "2010_000961",
        "support_name": "2008_007498"
    },
    {
        "query_name": "2010_003418",
        "support_name": "2009_001160"
    },
    {
        "query_name": "2010_004419",
        "support_name": "2010_005888"
    },
    {
        "query_name": "2007_002400",
        "support_name": "2010_005428"
    },
    {
        "query_name": "2007_004143",
        "support_name": "2009_003498"
    },
    {
        "query_name": "2007_008051",
        "support_name": "2010_001995"
    },
    {
        "query_name": "2008_002358",
        "support_name": "2007_005600"
    },
    {
        "query_name": "2008_003858",
        "support_name": "2009_003080"
    },
    {
        "query_name": "2008_003976",
        "support_name": "2010_003127"
    },
    {
        "query_name": "2009_000446",
        "support_name": "2009_003504"
    },
    {
        "query_name": "2009_000828",
        "support_name": "2008_001580"
    }
]